papr/__init__.py
papr/__main__.py
papr/cli.py
papr/tests.py
papr/html/footer.html
papr/html/header.html
papr/lib/__init__.py
papr/lib/abstract.py
papr/lib/cmd_add.py
papr/lib/cmd_config.py
papr/lib/cmd_default.py
papr/lib/cmd_fetch.py
papr/lib/cmd_init.py
papr/lib/cmd_last.py
papr/lib/cmd_list.py
papr/lib/cmd_read.py
papr/lib/cmd_search.py
papr/lib/config.py
papr/lib/console.py
papr/lib/db.py
papr/lib/edit.py
papr/lib/help.py
papr/lib/html.py
papr/lib/latest_version.py
papr/lib/paper.py
papr/lib/repository.py
papr/lib/termin.py
papr/lib/termout.py
papr/lib/tools.py
papr/lib/ui.py
papr/lib/ui_scrollview.py
papr/lib/migration/__init__.py
papr/lib/migration/functions.py
papr/lib/migration/v1_db.py
papr/lib/migration/v1_paper.py
papr/lib/migration/v1_repository.py
papr-0.0.20.dist-info/LICENSE
papr-0.0.20.dist-info/METADATA
papr-0.0.20.dist-info/WHEEL
papr-0.0.20.dist-info/entry_points.txt
papr-0.0.20.dist-info/top_level.txt
papr-0.0.20.dist-info/RECORD
