Metadata-Version: 2.1
Name: papr
Version: 0.0.20
Summary: A command line tool to manage scientific papers.
Home-page: https://github.com/daniel-e/papr
Author: Daniel Etzold
Author-email: detzold@gmail.com
License: UNKNOWN
Platform: UNKNOWN
Classifier: Programming Language :: Python :: 3
Classifier: License :: OSI Approved :: MIT License
Classifier: Operating System :: OS Independent
Requires-Dist: Markdown
Requires-Dist: bs4
Requires-Dist: pyyaml
Requires-Dist: termcolor
